{
  "xdaeqnsn": { "active": "1", "comment": "dntlcb3", "translation": "wzja2r8u" },
  "3p9xnasq": { "active": "1", "comment": "dntlcb6", "translation": "wzja2r8u" },
  "dfc1qg7q": { "active": "1", "comment": "kddnhdsl53", "translation": "wzja2r8u" },
  "rnrafenp": { "active": "1", "comment": "dntlt3", "translation": "wzja2r8u" },
  "xbebb0ep": { "active": "1", "comment": "dntlt6", "translation": "wzja2r8u" },
  "sy439qs7": { "active": "1", "comment": "kddnhdslt5", "translation": "wzja2r8u" },

  "zyizm02d": { "active": "1", "comment": "nmma", "translation": "wzja2r8u" },
  "mf20ff7a": { "active": "1", "comment": "nuan", "translation": "wzja2r8u" },
  "3k4ailsn": { "active": "1", "comment": "anen", "translation": "wzja2r8u" },
  "9xk7r4xw": { "active": "1", "comment": "cufe", "translation": "wzja2r8u" },
  "1zk75ibq": { "active": "1", "comment": "ts16", "translation": "wzja2r8u" },
  "js048l8i": { "active": "1", "comment": "anm1", "translation": "wzja2r8u" },
  "xdh8bmv8": { "active": "1", "comment": "anm2", "translation": "wzja2r8u" },
  "1p5dogdd": { "active": "1", "comment": "caac", "translation": "wzja2r8u" },
  "ikqhn97c": { "active": "1", "comment": "cota", "translation": "wzja2r8u" },
  "k45uum72": { "active": "1", "comment": "caac", "translation": "wzja2r8u" },
  "vdzbauap": { "active": "1", "comment": "ans3", "translation": "wzja2r8u" },
  "1cq3bria": { "active": "1", "comment": "meo2", "translation": "wzja2r8u" },
  "54efb8sw": { "active": "1", "comment": "cmv1", "translation": "wzja2r8u" },
  "geqacp08": { "active": "1", "comment": "nbvn", "translation": "wzja2r8u" },
  "oydrzn5h": { "active": "1", "comment": "tvn1", "translation": "wzja2r8u" },
  "eifymrwl": { "active": "1", "comment": "vohc", "translation": "wzja2r8u" },
  "3embztxc": { "active": "1", "comment": "cmv2", "translation": "wzja2r8u" },
  "2a0achw1": { "active": "1", "comment": "cvvn", "translation": "wzja2r8u" },
  "r03d30z8": { "active": "1", "comment": "hccv", "translation": "wzja2r8u" },
  "gku0mbzd": { "active": "1", "comment": "tvn2", "translation": "wzja2r8u" },
  "i2gm4502": { "active": "1", "comment": "azdq", "translation": "wzja2r8u" },
  "m3dbcldu": { "active": "1", "comment": "madp", "translation": "wzja2r8u" },
  "7p23wz2j": { "active": "1", "comment": "amdk", "translation": "wzja2r8u" },
  "tpghx8fa": { "active": "1", "comment": "mjs1", "translation": "wzja2r8u" },
  "0rlvsak8": { "active": "1", "comment": "stmm", "translation": "wzja2r8u" },
  "jkgzc0u2": { "active": "1", "comment": "mjs1", "translation": "wzja2r8u" },
  "tcow47vx": { "active": "1", "comment": "gtcc", "translation": "wzja2r8u" },
  "d528aoxu": { "active": "1", "comment": "mnic", "translation": "wzja2r8u" },
  "dp3t9cs2": { "active": "1", "comment": "amh1", "translation": "wzja2r8u" },
  "xeeebbi4": { "active": "1", "comment": "maas", "translation": "wzja2r8u" },
  "qfo8cm35": { "active": "1", "comment": "macf", "translation": "wzja2r8u" },
  "blsc47z2": { "active": "1", "comment": "mian", "translation": "wzja2r8u" },
  "z4yzdddd": { "active": "1", "comment": "lsdt", "translation": "wzja2r8u" },

  "c9tvjjdh": { "active": "1", "comment": "cmvc", "translation": "wzja2r8u" },
  "uhwnouqq": { "active": "1", "comment": "anmc", "translation": "wzja2r8u" },
  "3htgr97o": { "active": "1", "comment": "tcmm", "translation": "wzja2r8u" },
  "43wy9d4l": { "active": "1", "comment": "tctt", "translation": "wzja2r8u" },
  "zxrzud3f": { "active": "1", "comment": "tctd", "translation": "wzja2r8u" },
  "ngt4c1mk": { "active": "1", "comment": "pkmm", "translation": "wzja2r8u" },
  "ljztjai8": { "active": "1", "comment": "cn96", "translation": "wzja2r8u" },
  "y1y4ijaq": { "active": "1", "comment": "mvtd", "translation": "wzja2r8u" },
  "f0lih31z": { "active": "1", "comment": "cneo", "translation": "wzja2r8u" },
  "zkrmiiv2": { "active": "1", "comment": "mvch", "translation": "wzja2r8u" },
  "nmbxllj0": { "active": "1", "comment": "mitd", "translation": "wzja2r8u" },
  "o9b7mvml": { "active": "1", "comment": "tttn", "translation": "wzja2r8u" },
  "byvwexa8": { "active": "1", "comment": "ttmm", "translation": "wzja2r8u" },
  "ij05oq3j": { "active": "1", "comment": "tttt", "translation": "wzja2r8u" },
  "0ak32qm0": { "active": "1", "comment": "tttd", "translation": "wzja2r8u" },

  "3c3w7j3e": { "active": "1", "comment": "bhcm.mm.hhttllll.1", "translation": "" },
  "yfkjse0n": { "active": "1", "comment": "brmu.mm.hhttllll.1", "translation": "" },
  "frpg14kz": { "active": "1", "comment": "hccv.mm.hhttllll.1", "translation": "" },
  "mfq2fqa1": { "active": "1", "comment": "bnfr.mm.hhttllll.1", "translation": "" },
  "rurdgpih": { "active": "1", "comment": "azdq.mm.hhttllll.1", "translation": "" },
  "rrt2f7vk": { "active": "1", "comment": "bsqg.mm.hhttllll.1", "translation": "" },
  "hl7wxldt": { "active": "1", "comment": "zhfa.mm.hhttllll.1", "translation": "" },
  "uwqww8sj": { "active": "1", "comment": "modp.mm.hhttllll.1", "translation": "" },
  "kugl0gma": { "active": "1", "comment": "modp.mm.hhttllll.2", "translation": "" },
  "ttczn2ub": { "active": "1", "comment": "modp.mm.hhttllll.3", "translation": "" },
  "mbxkwhya": { "active": "1", "comment": "moda.mm.hhttllll.1", "translation": "" },
  "nrarncjo": { "active": "1", "comment": "bjcx.mm.hhttllll.1", "translation": "" },
  "nw1wdbsy": { "active": "1", "comment": "zhfa.mm.hhttllll.2", "translation": "" },
  "gxrcky82": { "active": "1", "comment": "amdk.mm.hhttllll.1", "translation": "" },
  "5saajpfr": { "active": "1", "comment": "hccv.mm.qtdapdvt.1", "translation": "" },
  "7xsbv3ym": { "active": "1", "comment": "bhcm.mm.qtdapdvt.1", "translation": "" },
  "hw71kukx": { "active": "1", "comment": "bhcm.mm.qtdapdvt.1", "translation": "" },
  "vv43j9zo": { "active": "1", "comment": "mmep.mm.qtdapdvt.1", "translation": "" },
  "b930g4xu": { "active": "1", "comment": "bnfr.mm.qtdapdvt.1", "translation": "" },
  "w0x5ng5f": { "active": "1", "comment": "macf.mm.qtdapdvt.1", "translation": "" },
  "8dmkt3we": { "active": "1", "comment": "ans3.mm.qtdapdvt.1", "translation": "" },
  "w7dn3a8k": { "active": "1", "comment": "vhco.mm.qtdapdvt.1", "translation": "" },
  "sx1owkhg": { "active": "1", "comment": "azdq.mm.qtdapdvt.1", "translation": "" },
  "jm0e8er5": { "active": "1", "comment": "amdk.mm.qtdapdvt.1", "translation": "" },
  "kmu3d90k": { "active": "1", "comment": "moda.mm.qtdapdvt.1", "translation": "" },
  "57n53ze4": { "active": "1", "comment": "bmtw.mm.qtdapdvt.1", "translation": "" },
  "xcd2ypuo": { "active": "1", "comment": "bmtw.mm.qtdapdvt.2", "translation": "" },
  "ixmyq902": { "active": "1", "comment": "chco.mm.qtdapdvt.1", "translation": "" },
  "y1kw48m5": { "active": "1", "comment": "gdcz.mm.qtdapdvt.1", "translation": "" },
  "84hmdmmc": { "active": "1", "comment": "ngbh.mm.qtdapdvt.1", "translation": "" },
  "hbljnbqs": { "active": "1", "comment": "kyqs.mm.qtdapdvt.1", "translation": "" },
  "8qzu4vip": { "active": "1", "comment": "brmu.mm.hptctbcn.1", "translation": "" },
  "3b0zcfp9": { "active": "1", "comment": "bhcm.mm.hptctbcn.1", "translation": "" },
  "5h3ygtel": { "active": "1", "comment": "bsqg.mm.hptctbcn.1", "translation": "" },
  "32128lhk": { "active": "1", "comment": "hccv.mm.hptctbcn.1", "translation": "" },
  "1v0bj98a": { "active": "1", "comment": "bnfr.mm.hptctbcn.1", "translation": "" },
  "n2adgq9p": { "active": "1", "comment": "vhco.mm.hptctbcn.1", "translation": "" },
  "c1p7ycw3": { "active": "1", "comment": "azdq.mm.hptctbcn.1", "translation": "" },
  "9o4ueczg": { "active": "1", "comment": "amdk.mm.hptctbcn.1", "translation": "" },
  "kqh982ba": { "active": "1", "comment": "moda.mm.hptctbcn.1", "translation": "" },
  "d4bt9uyp": { "active": "1", "comment": "bmtw.mm.hptctbcn.1", "translation": "" },
  "ak5lszwm": { "active": "1", "comment": "gdcz.mm.hptctbcn.1", "translation": "" },
  "jje4vsol": { "active": "1", "comment": "bjcx.mm.hptctbcn.1", "translation": "" },
  "vtofeon7": { "active": "1", "comment": "jnqu.mm.hptctbcn.1", "translation": "" },
  "shaszpg8": { "active": "1", "comment": "bhcm.mm.dvdldddt.1", "translation": "" },
  "dxclj97j": { "active": "1", "comment": "brmu.mm.dvdldddt.1", "translation": "" },
  "jmwsbbsc": { "active": "1", "comment": "bsqg.mm.dvdldddt.1", "translation": "" },
  "h7gqu1vg": { "active": "1", "comment": "hccv.mm.dvdldddt.1", "translation": "" },
  "s5nsa1bc": { "active": "1", "comment": "bnfr.mm.dvdldddt.1", "translation": "" },
  "qzzhkdkp": { "active": "1", "comment": "mmep.mm.dvdldddt.1", "translation": "" },
  "pglydxe0": { "active": "1", "comment": "azdq.mm.dvdldddt.1", "translation": "" },
  "snbyej5l": { "active": "1", "comment": "amdk.mm.dvdldddt.1", "translation": "" },
  "rzli3pes": { "active": "1", "comment": "wnlu.mm.dvdldddt.1", "translation": "" },
  "e8jc8c2k": { "active": "1", "comment": "gdcz.mm.dvdldddt.1", "translation": "" },
  "fk9yknqh": { "active": "1", "comment": "shcy.mm.dvdldddt.1", "translation": "" },
  "w9u2a8hy": { "active": "1", "comment": "lmhh.mm.dvdldddt.1", "translation": "" },
  "b9jwvfeo": { "active": "1", "comment": "brmu.mm.lpkttsdt.1", "translation": "" },
  "afehcx8v": { "active": "1", "comment": "bhcm.mm.lpkttsdt.1", "translation": "" },
  "71zzntn0": { "active": "1", "comment": "hccv.mm.lpkttsdt.1", "translation": "" },
  "wdai2b0a": { "active": "1", "comment": "bnfr.mm.lpkttsdt.1", "translation": "" },
  "zyamz5yu": { "active": "1", "comment": "azdq.mm.lpkttsdt.1", "translation": "" },
  "ssimb9l0": { "active": "1", "comment": "huay.mm.lpkttsdt.1", "translation": "" },
  "x4lypdhh": { "active": "1", "comment": "bmtw.mm.lpkttsdt.1", "translation": "" },
  "4ras1zkx": { "active": "1", "comment": "zhfa.mm.lpkttsdt.1", "translation": "" },
  "yj41bcwv": { "active": "1", "comment": "tvn2.mm.lpkttsdt.1", "translation": "" },
  "uq9bfn1o": { "active": "1", "comment": "mmep.mm.lpkttsdt.1", "translation": "" },
  "z1mcpx33": { "active": "1", "comment": "vhco.mm.lpkttsdt.1", "translation": "" },
  "dxou0j5m": { "active": "1", "comment": "amdk.mm.lpkttsdt.1", "translation": "" },
  "1i0evd2p": { "active": "1", "comment": "gdcz.mm.lpkttsdt.1", "translation": "" },
  "vc1zh50r": { "active": "1", "comment": "shhs.mm.lpkttsdt.1", "translation": "" },
  "4xxbj4d7": { "active": "1", "comment": "enra.mm.lpkttsdt.1", "translation": "" },
  "ch37lgev": { "active": "1", "comment": "jnqu.mm.lpkttsdt.1", "translation": "" },
  "tyimcsk5": { "active": "1", "comment": "huay.mm.lpkttsdt.2", "translation": "" },
  "w48gxm2f": { "active": "1", "comment": "bhcm.mm.ccccvdvt.1", "translation": "" },
  "44hnzw29": { "active": "1", "comment": "hccv.mm.ccccvdvt.1", "translation": "" },
  "bhlfolar": { "active": "1", "comment": "huay.mm.ccccvdvt.1", "translation": "" },
  "iuk7s22g": { "active": "1", "comment": "bnfr.mm.ccccvdvt.1", "translation": "" },
  "c2adon81": { "active": "1", "comment": "azdq.mm.ccccvdvt.1", "translation": "" },
  "ui59miiq": { "active": "1", "comment": "jsef.mm.ccccvdvt.1", "translation": "" },
  "pvg5r5b5": { "active": "1", "comment": "mmep.mm.ccccvdvt.1", "translation": "" },
  "x5dk44wo": { "active": "1", "comment": "modp.mm.ccccvdvt.1", "translation": "" },
  "yp44x13h": { "active": "1", "comment": "modp.mm.ccccvdvt.2", "translation": "" },
  "noqiuiif": { "active": "1", "comment": "modp.mm.ccccvdvt.3", "translation": "" },
  "28oneoym": { "active": "1", "comment": "ans3.mm.ccccvdvt.1", "translation": "" },
  "lys5uyys": { "active": "1", "comment": "vhco.mm.ccccvdvt.1", "translation": "" },
  "hzt5eavd": { "active": "1", "comment": "haeu.mm.ccccvdvt.1", "translation": "" },
  "bdj0nt3f": { "active": "1", "comment": "gdcz.mm.ccccvdvt.1", "translation": "" },
  "bqgfwaf2": { "active": "1", "comment": "zeno.mm.ccccvdvt.1", "translation": "" },
  "lvbw9tcu": { "active": "1", "comment": "zhfa.mm.ccccvdvt.1", "translation": "" },
  "vsfd35jg": { "active": "1", "comment": "jnqu.mm.ccccvdvt.1", "translation": "" },
  "eymsyqyo": { "active": "1", "comment": "kyqs.mm.ccccvdvt.1", "translation": "" },
  "9k4xg2j7": { "active": "1", "comment": "amdk.mm.ccccvdvt.1", "translation": "" },
  "2qh5cw2d": { "active": "1", "comment": "brmu.mm.vtvtvvtt.1", "translation": "" },
  "0uxlpr2u": { "active": "1", "comment": "bhcm.mm.vtvtvvtt.1", "translation": "" },
  "3f7l2nds": { "active": "1", "comment": "hccv.mm.vtvtvvtt.1", "translation": "" },
  "et0g3rzt": { "active": "1", "comment": "moda.mm.vtvtvvtt.1", "translation": "" },
  "gaz2xplf": { "active": "1", "comment": "bnfr.mm.vtvtvvtt.1", "translation": "" },
  "tg7yed3t": { "active": "1", "comment": "vhco.mm.vtvtvvtt.1", "translation": "" },
  "5izme5oi": { "active": "1", "comment": "azdq.mm.vtvtvvtt.1", "translation": "" },
  "su8t8iy5": { "active": "1", "comment": "amdk.mm.vtvtvvtt.1", "translation": "" },
  "ph8e5qgb": { "active": "1", "comment": "chco.mm.vtvtvvtt.1", "translation": "" },
  "axbqjt0w": { "active": "1", "comment": "zhfa.mm.vtvtvvtt.1", "translation": "" },
  "ixqw1bs5": { "active": "1", "comment": "kyqs.mm.vtvtvvtt.1", "translation": "" },
  "p7r0g9ko": { "active": "1", "comment": "bhcm.mm.mmhhtttt.1", "translation": "" },
  "mp2l7rub": { "active": "1", "comment": "brmu.mm.mmhhtttt.1", "translation": "" },
  "wifhajqb": { "active": "1", "comment": "hccv.mm.mmhhtttt.1", "translation": "" },
  "cgqngcn2": { "active": "1", "comment": "jnqu.mm.mmhhtttt.1", "translation": "" },
  "jvz24swf": { "active": "1", "comment": "bnfr.mm.mmhhtttt.1", "translation": "" },
  "4hmoouxc": { "active": "1", "comment": "ans3.mm.mmhhtttt.1", "translation": "" },
  "fnrs1uxf": { "active": "1", "comment": "vhco.mm.mmhhtttt.1", "translation": "" },
  "2ru33gzj": { "active": "1", "comment": "azdq.mm.mmhhtttt.1", "translation": "" },
  "9fq3ek7h": { "active": "1", "comment": "amdk.mm.mmhhtttt.1", "translation": "" },
  "b50xmhdu": { "active": "1", "comment": "gdcz.mm.mmhhtttt.1", "translation": "" },
  "cbydw0nt": { "active": "1", "comment": "huay.mm.mmhhtttt.1", "translation": "" },
  "ww7eoofz": { "active": "1", "comment": "brmu.mm.hltqncpd.1", "translation": "" },
  "pmkfvoct": { "active": "1", "comment": "hccv.mm.hltqncpd.1", "translation": "" },
  "0q85sxy2": { "active": "1", "comment": "mmep.mm.hltqncpd.1", "translation": "" },
  "qhi05lb7": { "active": "1", "comment": "zhfa.mm.hltqncpd.1", "translation": "" },
  "u03mwc8d": { "active": "1", "comment": "azdq.mm.hltqncpd.1", "translation": "" },
  "gp3bhpjr": { "active": "1", "comment": "bhcm.mm.hltqncpd.1", "translation": "" },
  "mswz22dq": { "active": "1", "comment": "bsqg.mm.hltqncpd.1", "translation": "" },
  "vf45s1kn": { "active": "1", "comment": "bnfr.mm.hltqncpd.1", "translation": "" },
  "l0sabzas": { "active": "1", "comment": "ans3.mm.hltqncpd.1", "translation": "" },
  "ncpzbdz5": { "active": "1", "comment": "amdk.mm.hltqncpd.1", "translation": "" },
  "7bva4jhh": { "active": "1", "comment": "moda.mm.hltqncpd.1", "translation": "" },
  "d2xh3oub": { "active": "1", "comment": "jnqu.mm.hltqncpd.1", "translation": "" },
  "jlp2sk8e": { "active": "1", "comment": "bhcm.mm.ttttllaa.1", "translation": "" },
  "dg0hdu98": { "active": "1", "comment": "hccv.mm.ttttllaa.1", "translation": "" },
  "r5buang3": { "active": "1", "comment": "kyqs.mm.ttttllaa.1", "translation": "" },
  "qi3v1oqw": { "active": "1", "comment": "azdq.mm.ttttllaa.1", "translation": "" },
  "9dlewtsh": { "active": "1", "comment": "bnfr.mm.ttttllaa.1", "translation": "" },
  "zihb08e4": { "active": "1", "comment": "shhs.mm.ttttllaa.1", "translation": "" },
  "cqpquqa5": { "active": "1", "comment": "kyqs.mm.ttttllaa.2", "translation": "" },
  "5yj210p3": { "active": "1", "comment": "ans3.mm.ttttllaa.1", "translation": "" },
  "qc409wcl": { "active": "1", "comment": "amdk.mm.ttttllaa.1", "translation": "" },
  "g5gamdpe": { "active": "1", "comment": "gdcz.mm.ttttllaa.1", "translation": "" },
  "ubn87sku": { "active": "1", "comment": "brmu.mm.qpbcnant.1", "translation": "" },
  "mpxeolc9": { "active": "1", "comment": "hccv.mm.qpbcnant.1", "translation": "" },
  "rdb3bp4g": { "active": "1", "comment": "bsqg.mm.qpbcnant.1", "translation": "" },
  "u8hr9tg9": { "active": "1", "comment": "bnfr.mm.qpbcnant.1", "translation": "" },
  "831e91qh": { "active": "1", "comment": "azdq.mm.qpbcnant.1", "translation": "" },
  "jjvovos0": { "active": "1", "comment": "bhcm.mm.qpbcnant.1", "translation": "" },
  "sm5yqcsp": { "active": "1", "comment": "modp.mm.qpbcnant.1", "translation": "" },
  "c80x35nc": { "active": "1", "comment": "haeu.mm.qpbcnant.1", "translation": "" },
  "o5j4qriy": { "active": "1", "comment": "amdk.mm.qpbcnant.1", "translation": "" },
  "2ysfh94h": { "active": "1", "comment": "ans3.mm.qpbcnant.1", "translation": "" },
  "40i3wy58": { "active": "1", "comment": "haeu.mm.qpbcnant.2", "translation": "" },
  "fctgi7kk": { "active": "1", "comment": "huay.mm.qpbcnant.1", "translation": "" },
  "8vkg7gbx": { "active": "1", "comment": "gdcz.mm.qpbcnant.1", "translation": "" },
  "f1rr2kwu": { "active": "1", "comment": "jnqu.mm.qpbcnant.1", "translation": "" },
  "hbo4lm8z": { "active": "1", "comment": "brmu.mm.nsnxncnp.1", "translation": "" },
  "p8srpd7d": { "active": "1", "comment": "bhcm.mm.nsnxncnp.1", "translation": "" },
  "qv5kojhz": { "active": "1", "comment": "hccv.mm.nsnxncnp.1", "translation": "" },
  "u7iihcdd": { "active": "1", "comment": "mmep.mm.nsnxncnp.1", "translation": "" },
  "2zckvauh": { "active": "1", "comment": "bnfr.mm.nsnxncnp.1", "translation": "" },
  "zudkqw5z": { "active": "1", "comment": "ans3.mm.nsnxncnp.1", "translation": "" },
  "kuzff1b2": { "active": "1", "comment": "azdq.mm.nsnxncnp.1", "translation": "" },
  "pik7vu3e": { "active": "1", "comment": "amdk.mm.nsnxncnp.1", "translation": "" },
  "dtj83zb4": { "active": "1", "comment": "bmtw.mm.nsnxncnp.1", "translation": "" },
  "45cmt9qj": { "active": "1", "comment": "bmtw.mm.nsnxncnp.2", "translation": "" },
  "5xwskpka": { "active": "1", "comment": "jnqu.mm.nsnxncnp.1", "translation": "" },
  "pbdozsxq": { "active": "1", "comment": "bhcm.mm.qqttpptt.1", "translation": "" },
  "d2epkhov": { "active": "1", "comment": "hccv.mm.qqttpptt.1", "translation": "" },
  "38octytq": { "active": "1", "comment": "brmu.mm.qqttpptt.1", "translation": "" },
  "x7keokx0": { "active": "1", "comment": "mmep.mm.qqttpptt.1", "translation": "" },
  "0vrtri8b": { "active": "1", "comment": "bnfr.mm.qqttpptt.1", "translation": "" },
  "dxkhg11y": { "active": "1", "comment": "azdq.mm.qqttpptt.1", "translation": "" },
  "f8pjozy4": { "active": "1", "comment": "amdk.mm.qqttpptt.1", "translation": "" },
  "lhsq52x2": { "active": "1", "comment": "zgjd.mm.qqttpptt.1", "translation": "" },
  "tbedzevs": { "active": "1", "comment": "zhfa.mm.qqttpptt.1", "translation": "" },
  "tbzu2tu2": { "active": "1", "comment": "jnqu.mm.qqttpptt.1", "translation": "" },
  "k21dgvlj": { "active": "1", "comment": "bhcm.mm.pndhttns.1", "translation": "" },
  "dnlrbem1": { "active": "1", "comment": "hccv.mm.pndhttns.1", "translation": "" },
  "0o2ufabk": { "active": "1", "comment": "moda.mm.pndhttns.1", "translation": "" },
  "qlwrd0m4": { "active": "1", "comment": "zhfa.mm.pndhttns.1", "translation": "" },
  "cqnt1kyy": { "active": "1", "comment": "azdq.mm.pndhttns.1", "translation": "" },
  "0tu1qpqq": { "active": "1", "comment": "amdk.mm.pndhttns.1", "translation": "" },
  "v7evyume": { "active": "1", "comment": "gdcz.mm.pndhttns.1", "translation": "" },
  "noolsetk": { "active": "1", "comment": "jnqu.mm.pndhttns.1", "translation": "" },
  "tglhb214": { "active": "1", "comment": "bhcm.mm.vtdtvpdd.1", "translation": "" },
  "cf9y10ta": { "active": "1", "comment": "brmu.mm.vtdtvpdd.1", "translation": "" },
  "z8dr8959": { "active": "1", "comment": "hccv.mm.vtdtvpdd.1", "translation": "" },
  "c8480u7k": { "active": "1", "comment": "kyqs.mm.vtdtvpdd.1", "translation": "" },
  "whea3dmp": { "active": "1", "comment": "azdq.mm.vtdtvpdd.1", "translation": "" },
  "wvw47fse": { "active": "1", "comment": "ngbh.mm.vtdtvpdd.1", "translation": "" },
  "kehvpwci": { "active": "1", "comment": "jesf.mm.vtdtvpdd.1", "translation": "" },
  "0l4l3dxm": { "active": "1", "comment": "mmep.mm.vtdtvpdd.1", "translation": "" },
  "2fg241vs": { "active": "1", "comment": "bnfr.mm.vtdtvpdd.1", "translation": "" },
  "gt4vutt2": { "active": "1", "comment": "vhco.mm.vtdtvpdd.1", "translation": "" },
  "8a1tmxop": { "active": "1", "comment": "amdk.mm.vtdtvpdd.1", "translation": "" },
  "djgkgnwx": { "active": "1", "comment": "bhcm.mm.tbaddbab.1", "translation": "" },
  "o9qscjmj": { "active": "1", "comment": "brmu.mm.tbaddbab.1", "translation": "" },
  "vv4bot4f": { "active": "1", "comment": "hccv.mm.tbaddbab.1", "translation": "" },
  "ekn7rtfy": { "active": "1", "comment": "bsqg.mm.tbaddbab.1", "translation": "" },
  "vfdwbzg1": { "active": "1", "comment": "azdq.mm.tbaddbab.1", "translation": "" },
  "nsyundjo": { "active": "1", "comment": "mmep.mm.tbaddbab.1", "translation": "" },
  "rbuicojg": { "active": "1", "comment": "zeno.mm.tbaddbab.1", "translation": "" },
  "owjtfngx": { "active": "1", "comment": "amdk.mm.tbaddbab.1", "translation": "" },
  "r2okhudc": { "active": "1", "comment": "ans3.mm.tbaddbab.1", "translation": "" },
  "tdce52s8": { "active": "1", "comment": "bnfr.mm.tbaddbab.1", "translation": "" },
  "xowuk7bn": { "active": "1", "comment": "gdcz.mm.tbaddbab.1", "translation": "" },
  "i5k1md2j": { "active": "1", "comment": "kyqs.mm.tbaddbab.1", "translation": "" },
  "eejubi53": { "active": "1", "comment": "brmu.mm.ttkcknkt.1", "translation": "" },
  "lc11lphr": { "active": "1", "comment": "bhcm.mm.ttkcknkt.1", "translation": "" },
  "eycknkze": { "active": "1", "comment": "hccv.mm.ttkcknkt.1", "translation": "" },
  "snqyp5fv": { "active": "1", "comment": "kyqs.mm.ttkcknkt.1", "translation": "" },
  "w2syr1s5": { "active": "1", "comment": "azdq.mm.ttkcknkt.1", "translation": "" },
  "ngihnh7j": { "active": "1", "comment": "bsqg.mm.ttkcknkt.1", "translation": "" },
  "i29aj89f": { "active": "1", "comment": "mjs1.mm.ttkcknkt.1", "translation": "" },
  "r5fzhvq0": { "active": "1", "comment": "zeno.mm.ttkcknkt.1", "translation": "" },
  "03acysym": { "active": "1", "comment": "huay.mm.ttkcknkt.1", "translation": "" },
  "oej7mjgb": { "active": "1", "comment": "amdk.mm.ttkcknkt.1", "translation": "" },
  "2krmaoae": { "active": "1", "comment": "gdcz.mm.ttkcknkt.1", "translation": "" },
  "1yakzqup": { "active": "1", "comment": "shhs.mm.ttkcknkt.1", "translation": "" },
  "gniq0ils": { "active": "1", "comment": "ans3.mm.ttkcknkt.1", "translation": "" },
  "udvthqvt": { "active": "1", "comment": "jnqu.mm.ttkcknkt.1", "translation": "" },
  "5bjeexoh": { "active": "1", "comment": "brmu.mm.vdddtmdd.1", "translation": "" },
  "03fyil3r": { "active": "1", "comment": "bhcm.mm.vdddtmdd.1", "translation": "" },
  "jt05emb5": { "active": "1", "comment": "mmep.mm.vdddtmdd.1", "translation": "" },
  "iwm4cspi": { "active": "1", "comment": "bnfr.mm.vdddtmdd.1", "translation": "" },
  "2op91b98": { "active": "1", "comment": "modp.mm.vdddtmdd.1", "translation": "" },
  "fbgw1nsj": { "active": "1", "comment": "modp.mm.vdddtmdd.2", "translation": "" },
  "lociztdu": { "active": "1", "comment": "modp.mm.vdddtmdd.3", "translation": "" },
  "2f5t7orc": { "active": "1", "comment": "azdq.mm.vdddtmdd.1", "translation": "" },
  "0b9gacdw": { "active": "1", "comment": "amdk.mm.vdddtmdd.1", "translation": "" },
  "lpzpp8ru": { "active": "1", "comment": "haeu.mm.vdddtmdd.1", "translation": "" },
  "5vzjc0ve": { "active": "1", "comment": "ngbh.mm.vdddtmdd.1", "translation": "" },
  "v54590ki": { "active": "1", "comment": "jnqu.mm.vdddtmdd.1", "translation": "" },
  "05vto88l": { "active": "1", "comment": "zhfa.mm.vdddtmdd.1", "translation": "" },
  "dmne9zuc": { "active": "1", "comment": "bhcm.mm.nnhkvtvc.1", "translation": "" },
  "gao1mg3j": { "active": "1", "comment": "brmu.mm.nnhkvtvc.1", "translation": "" },
  "xoq1ls5k": { "active": "1", "comment": "hccv.mm.nnhkvtvc.1", "translation": "" },
  "45bj2w8v": { "active": "1", "comment": "mmep.mm.nnhkvtvc.1", "translation": "" },
  "a1zz9zeb": { "active": "1", "comment": "bnfr.mm.nnhkvtvc.1", "translation": "" },
  "pcbalviu": { "active": "1", "comment": "vhco.mm.nnhkvtvc.1", "translation": "" },
  "f5pougvu": { "active": "1", "comment": "azdq.mm.nnhkvtvc.1", "translation": "" },
  "ctmz9rea": { "active": "1", "comment": "amdk.mm.nnhkvtvc.1", "translation": "" },
  "24ae31kz": { "active": "1", "comment": "macf.mm.nnhkvtvc.1", "translation": "" },
  "75zqy0hm": { "active": "1", "comment": "moda.mm.nnhkvtvc.1", "translation": "" },
  "epq425ef": { "active": "1", "comment": "zhfa.mm.nnhkvtvc.1", "translation": "" },
  "cvr8ohib": { "active": "1", "comment": "kyqs.mm.nnhkvtvc.1", "translation": "" },
  "zkjlc209": { "active": "1", "comment": "brmu.mm.nttpttkn.1", "translation": "" },
  "p9pe91hs": { "active": "1", "comment": "bhcm.mm.nttpttkn.1", "translation": "" },
  "gyu4lvsr": { "active": "1", "comment": "hccv.mm.nttpttkn.1", "translation": "" },
  "yba9m4gg": { "active": "1", "comment": "bsqg.mm.nttpttkn.1", "translation": "" }
}