{
  "xdaeqnsn": { "active": "1", "comment": "dntlcb3", "translation": "wzja2r8u" },
  "3p9xnasq": { "active": "1", "comment": "dntlcb6", "translation": "wzja2r8u" },
  "dfc1qg7q": { "active": "1", "comment": "kddnhdsl53", "translation": "wzja2r8u" },
  "rnrafenp": { "active": "1", "comment": "dntlt3", "translation": "wzja2r8u" },
  "xbebb0ep": { "active": "1", "comment": "dntlt6", "translation": "wzja2r8u" },
  "sy439qs7": { "active": "1", "comment": "kddnhdslt5", "translation": "wzja2r8u" },

  "zyizm02d": { "active": "1", "comment": "nmma", "translation": "wzja2r8u" },
  "mf20ff7a": { "active": "1", "comment": "nuan", "translation": "wzja2r8u" },
  "3k4ailsn": { "active": "1", "comment": "anen", "translation": "wzja2r8u" },
  "9xk7r4xw": { "active": "1", "comment": "cufe", "translation": "wzja2r8u" },
  "1zk75ibq": { "active": "1", "comment": "ts16", "translation": "wzja2r8u" },
  "js048l8i": { "active": "1", "comment": "anm1", "translation": "wzja2r8u" },
  "xdh8bmv8": { "active": "1", "comment": "anm2", "translation": "wzja2r8u" },
  "1p5dogdd": { "active": "1", "comment": "caac", "translation": "wzja2r8u" },
  "ikqhn97c": { "active": "1", "comment": "cota", "translation": "wzja2r8u" },
  "k45uum72": { "active": "1", "comment": "caac", "translation": "wzja2r8u" },
  "vdzbauap": { "active": "1", "comment": "ans3", "translation": "wzja2r8u" },
  "1cq3bria": { "active": "1", "comment": "meo2", "translation": "wzja2r8u" },
  "54efb8sw": { "active": "1", "comment": "cmv1", "translation": "wzja2r8u" },
  "geqacp08": { "active": "1", "comment": "nbvn", "translation": "wzja2r8u" },
  "oydrzn5h": { "active": "1", "comment": "tvn1", "translation": "wzja2r8u" },
  "eifymrwl": { "active": "1", "comment": "vohc", "translation": "wzja2r8u" },
  "3embztxc": { "active": "1", "comment": "cmv2", "translation": "wzja2r8u" },
  "2a0achw1": { "active": "1", "comment": "cvvn", "translation": "wzja2r8u" },
  "r03d30z8": { "active": "1", "comment": "hccv", "translation": "wzja2r8u" },
  "gku0mbzd": { "active": "1", "comment": "tvn2", "translation": "wzja2r8u" },
  "i2gm4502": { "active": "1", "comment": "azdq", "translation": "wzja2r8u" },
  "m3dbcldu": { "active": "1", "comment": "madp", "translation": "wzja2r8u" },
  "7p23wz2j": { "active": "1", "comment": "amdk", "translation": "wzja2r8u" },
  "tpghx8fa": { "active": "1", "comment": "mjs1", "translation": "wzja2r8u" },
  "0rlvsak8": { "active": "1", "comment": "stmm", "translation": "wzja2r8u" },
  "jkgzc0u2": { "active": "1", "comment": "mjs1", "translation": "wzja2r8u" },
  "tcow47vx": { "active": "1", "comment": "gtcc", "translation": "wzja2r8u" },
  "d528aoxu": { "active": "1", "comment": "mnic", "translation": "wzja2r8u" },
  "dp3t9cs2": { "active": "1", "comment": "amh1", "translation": "wzja2r8u" },
  "xeeebbi4": { "active": "1", "comment": "maas", "translation": "wzja2r8u" },
  "qfo8cm35": { "active": "1", "comment": "macf", "translation": "wzja2r8u" },
  "blsc47z2": { "active": "1", "comment": "mian", "translation": "wzja2r8u" },
  "z4yzdddd": { "active": "1", "comment": "lsdt", "translation": "wzja2r8u" },

  "c9tvjjdh": { "active": "1", "comment": "cmvc", "translation": "wzja2r8u" },
  "uhwnouqq": { "active": "1", "comment": "anmc", "translation": "wzja2r8u" },
  "3htgr97o": { "active": "1", "comment": "tcmm", "translation": "wzja2r8u" },
  "43wy9d4l": { "active": "1", "comment": "tctt", "translation": "wzja2r8u" },
  "zxrzud3f": { "active": "1", "comment": "tctd", "translation": "wzja2r8u" },
  "ngt4c1mk": { "active": "1", "comment": "pkmm", "translation": "wzja2r8u" },
  "ljztjai8": { "active": "1", "comment": "cn96", "translation": "wzja2r8u" },
  "y1y4ijaq": { "active": "1", "comment": "mvtd", "translation": "wzja2r8u" },
  "f0lih31z": { "active": "1", "comment": "cneo", "translation": "wzja2r8u" },
  "zkrmiiv2": { "active": "1", "comment": "mvch", "translation": "wzja2r8u" },
  "nmbxllj0": { "active": "1", "comment": "mitd", "translation": "wzja2r8u" },
  "o9b7mvml": { "active": "1", "comment": "tttn", "translation": "wzja2r8u" },
  "byvwexa8": { "active": "1", "comment": "ttmm", "translation": "wzja2r8u" },
  "ij05oq3j": { "active": "1", "comment": "tttt", "translation": "wzja2r8u" },
  "0ak32qm0": { "active": "1", "comment": "tttd", "translation": "wzja2r8u" },

  "3c3w7j3e": { "active": "1", "comment": "bhcm.mm.hhttllll.1", "translation": "" },
  "yfkjse0n": { "active": "1", "comment": "brmu.mm.hhttllll.1", "translation": "" },
  "frpg14kz": { "active": "1", "comment": "hccv.mm.hhttllll.1", "translation": "" },
  "mfq2fqa1": { "active": "1", "comment": "bnfr.mm.hhttllll.1", "translation": "" },
  "rurdgpih": { "active": "1", "comment": "azdq.mm.hhttllll.1", "translation": "" },
  "rrt2f7vk": { "active": "1", "comment": "bsqg.mm.hhttllll.1", "translation": "" },
  "hl7wxldt": { "active": "1", "comment": "zhfa.mm.hhttllll.1", "translation": "" },
  "uwqww8sj": { "active": "1", "comment": "modp.mm.hhttllll.1", "translation": "" },
  "kugl0gma": { "active": "1", "comment": "modp.mm.hhttllll.2", "translation": "" },
  "ttczn2ub": { "active": "1", "comment": "modp.mm.hhttllll.3", "translation": "" },
  "mbxkwhya": { "active": "1", "comment": "moda.mm.hhttllll.1", "translation": "" },
  "nrarncjo": { "active": "1", "comment": "bjcx.mm.hhttllll.1", "translation": "" },
  "nw1wdbsy": { "active": "1", "comment": "zhfa.mm.hhttllll.2", "translation": "" },
  "gxrcky82": { "active": "1", "comment": "amdk.mm.hhttllll.1", "translation": "" },
  "5saajpfr": { "active": "1", "comment": "hccv.mm.qtdapdvt.1", "translation": "" },
  "7xsbv3ym": { "active": "1", "comment": "bhcm.mm.qtdapdvt.1", "translation": "" },
  "hw71kukx": { "active": "1", "comment": "bhcm.mm.qtdapdvt.1", "translation": "" },
  "vv43j9zo": { "active": "1", "comment": "mmep.mm.qtdapdvt.1", "translation": "" },
  "b930g4xu": { "active": "1", "comment": "bnfr.mm.qtdapdvt.1", "translation": "" },
  "w0x5ng5f": { "active": "1", "comment": "macf.mm.qtdapdvt.1", "translation": "" },
  "8dmkt3we": { "active": "1", "comment": "ans3.mm.qtdapdvt.1", "translation": "" },
  "w7dn3a8k": { "active": "1", "comment": "vhco.mm.qtdapdvt.1", "translation": "" },
  "sx1owkhg": { "active": "1", "comment": "azdq.mm.qtdapdvt.1", "translation": "" },
  "jm0e8er5": { "active": "1", "comment": "amdk.mm.qtdapdvt.1", "translation": "" },
  "kmu3d90k": { "active": "1", "comment": "moda.mm.qtdapdvt.1", "translation": "" },
  "57n53ze4": { "active": "1", "comment": "bmtw.mm.qtdapdvt.1", "translation": "" },
  "xcd2ypuo": { "active": "1", "comment": "bmtw.mm.qtdapdvt.2", "translation": "" }
}