{
  "ca2gpala": { "active": "1", "comment": "mmbbhhttllll", "href": ["ffhq0gea", "1redsad2", "xe9mdcct"], "identifier": "1", "innerHtml": "1redsad2", "title": ["ffhq0gea", "1redsad2"], "entity": "specimen" },
  "03em2flu": { "active": "1", "comment": "mmbbhhttllll", "href": ["ffhq0gea", "1redsad2", "jpefeyq0"], "identifier": "140", "innerHtml": "1redsad2", "title": ["ffhq0gea", "1redsad2"], "entity": "specimen" },
  "5f9va3jo": { "active": "1", "comment": "mmbbhhttllll", "href": ["ffhq0gea", "1redsad2", "9mjxix47"], "identifier": "1", "innerHtml": "1redsad2", "title": ["ffhq0gea", "1redsad2"], "entity": "specimen" },

  "ihedakvg": { "active": "1", "comment": "mmbbhhttllll", "href": ["ffhq0gea", "1redsad2", "sv1zy3zs"], "identifier": "1", "innerHtml": "sv1zy3zs", "title": ["ffhq0gea", "1redsad2"], "entity": "specimen" },
  "5vocvuwk": { "active": "1", "comment": "mmbbhhttllll", "href": ["ffhq0gea", "1redsad2", "nyezout9"], "identifier": "14-1144", "innerHtml": "nyezout9", "title": ["ffhq0gea", "1redsad2"], "entity": "specimen" },
  "naesrimu": { "active": "1", "comment": "mmbbhhttllll", "href": ["ffhq0gea", "1redsad2", "yxzic1j1"], "identifier": "1", "innerHtml": "yxzic1j1", "title": ["ffhq0gea", "1redsad2"], "entity": "specimen" },
  "7dk413tr": { "active": "1", "comment": "mmbbhhttllll", "href": ["ffhq0gea", "1redsad2", "kfdihizg"], "identifier": "1528", "innerHtml": "kfdihizg", "title": ["ffhq0gea", "1redsad2"], "entity": "specimen" },
  "un7ctiuw": { "active": "1", "comment": "mmbbhhttllll", "href": ["ffhq0gea", "1redsad2", "wsrgeo3w"], "identifier": "V71", "innerHtml": "wsrgeo3w", "title": ["ffhq0gea", "1redsad2"], "entity": "specimen" },
  "j1a5bpda": { "active": "1", "comment": "mmbbhhttllll", "href": ["ffhq0gea", "1redsad2", "qoajrwma"], "identifier": "426", "innerHtml": "qoajrwma", "title": ["ffhq0gea", "1redsad2"], "entity": "specimen" },
  "dbbyq9da": { "active": "1", "comment": "mmbbhhttllll", "href": ["ffhq0gea", "1redsad2", "lcgt1rxf"], "identifier": "129", "innerHtml": "lcgt1rxf", "title": ["ffhq0gea", "1redsad2"], "entity": "specimen" },
  "0sul2izl": { "active": "1", "comment": "mmbbhhttllll", "href": ["ffhq0gea", "1redsad2", "w0f13f17"], "identifier": "38-2", "innerHtml": "w0f13f17", "title": ["ffhq0gea", "1redsad2"], "entity": "specimen" },

  "hujd9yi9": { "active": "1", "comment": "mmbbhhttllll", "href": ["ffhq0gea", "1redsad2", "m8wqq7v9"], "identifier": "1", "innerHtml": "1redsad2", "title": ["ffhq0gea", "1redsad2"], "entity": "specimen" },
  "ss85paj9": { "active": "1", "comment": "mmbbhhttllll", "href": ["ffhq0gea", "1redsad2", "sv1zy3zs"], "identifier": "2", "innerHtml": "1redsad2", "title": ["ffhq0gea", "1redsad2"], "entity": "specimen" },
  "epjp5poa": { "active": "1", "comment": "mmbbhhttllll", "href": ["ffhq0gea", "1redsad2", "8s92npt8"], "identifier": "55-820-01", "innerHtml": "1redsad2", "title": ["ffhq0gea", "1redsad2"], "entity": "specimen" },

  "x8ylupyl": { "active": "1", "comment": "mmbbhhttllll", "href": ["ffhq0gea", "1redsad2", "wsrgeo3w"], "identifier": "V70", "innerHtml": "wsrgeo3w", "title": ["ffhq0gea", "1redsad2"], "entity": "specimen" },
  "ns2kui9e": { "active": "1", "comment": "mmbbhhttllll", "href": ["ffhq0gea", "1redsad2", "wsrgeo3w"], "identifier": "V72", "innerHtml": "wsrgeo3w", "title": ["ffhq0gea", "1redsad2"], "entity": "specimen" },
  "s8i0er9i": { "active": "1", "comment": "mmbbhhttllll", "href": ["ffhq0gea", "1redsad2", "w0f13f17"], "identifier": "38-1", "innerHtml": "w0f13f17", "title": ["ffhq0gea", "1redsad2"], "entity": "specimen" },
  "7jopev3b": { "active": "1", "comment": "mmbbhhttllll", "href": ["ffhq0gea", "1redsad2", "t7alai3m"], "identifier": "19", "innerHtml": "t7alai3m", "title": ["ffhq0gea", "1redsad2"], "entity": "specimen" }
}